pysurveycto/__init__.py
pysurveycto/pysurveycto.py
pysurveycto-0.0.15.dist-info/LICENSE.md
pysurveycto-0.0.15.dist-info/METADATA
pysurveycto-0.0.15.dist-info/WHEEL
pysurveycto-0.0.15.dist-info/top_level.txt
pysurveycto-0.0.15.dist-info/RECORD
