Metadata-Version: 2.1
Name: pysurveycto
Version: 0.0.15
Summary: Interacting with SurveyCTO using Python
Home-page: https://github.com/IDinsight/surveycto-python/
Author: Eric Dodge, Jeenu Thomas
Author-email: it@idinsight.org, Eric.Dodge@idinsight.org, Jeenu.Thomas@idinsight.org
Classifier: Programming Language :: Python :: 3
Classifier: Programming Language :: Python :: 3.4
Classifier: Programming Language :: Python :: 3.5
Classifier: Programming Language :: Python :: 3.6
Classifier: Programming Language :: Python :: 3.7
Classifier: License :: OSI Approved :: MIT License
Classifier: Operating System :: OS Independent
Requires-Python: >=3
License-File: LICENSE.md
Requires-Dist: requests >=2.0.0
Requires-Dist: urllib3 >=1.21.1
